hellouser.py
hellouser-0.0.2.dist-info/LICENSE
hellouser-0.0.2.dist-info/METADATA
hellouser-0.0.2.dist-info/WHEEL
hellouser-0.0.2.dist-info/top_level.txt
hellouser-0.0.2.dist-info/RECORD
